CHANGES.rst
DESCRIPTION.rst
LICENSE
MANIFEST.in
README.md
setup.py
src/wai.annotations.core.egg-info/PKG-INFO
src/wai.annotations.core.egg-info/SOURCES.txt
src/wai.annotations.core.egg-info/dependency_links.txt
src/wai.annotations.core.egg-info/entry_points.txt
src/wai.annotations.core.egg-info/namespace_packages.txt
src/wai.annotations.core.egg-info/requires.txt
src/wai.annotations.core.egg-info/top_level.txt
src/wai/annotations/core/__init__.py
src/wai/annotations/core/builder/_ConversionPipelineBuilder.py
src/wai/annotations/core/builder/_InlineDomainValidator.py
src/wai/annotations/core/builder/__init__.py
src/wai/annotations/core/builder/error/_BadDomain.py
src/wai/annotations/core/builder/error/_InputStageNotFirst.py
src/wai/annotations/core/builder/error/_StageAfterOutput.py
src/wai/annotations/core/builder/error/_StageInvalidForDomains.py
src/wai/annotations/core/builder/error/__init__.py
src/wai/annotations/core/component/_Component.py
src/wai/annotations/core/component/_ProcessorComponent.py
src/wai/annotations/core/component/_SinkComponent.py
src/wai/annotations/core/component/_SourceComponent.py
src/wai/annotations/core/component/__init__.py
src/wai/annotations/core/component/util/_AnnotationFileProcessor.py
src/wai/annotations/core/component/util/_Buffer.py
src/wai/annotations/core/component/util/_Enumerator.py
src/wai/annotations/core/component/util/_JSONFileWriter.py
src/wai/annotations/core/component/util/_LocalFileWriter.py
src/wai/annotations/core/component/util/_LocalFilenameSource.py
src/wai/annotations/core/component/util/_SeparateFileWriter.py
src/wai/annotations/core/component/util/_WithRandomness.py
src/wai/annotations/core/component/util/__init__.py
src/wai/annotations/core/component/util/_splitting.py
src/wai/annotations/core/domain/_Data.py
src/wai/annotations/core/domain/_DomainSpecifier.py
src/wai/annotations/core/domain/_Instance.py
src/wai/annotations/core/domain/__init__.py
src/wai/annotations/core/help/_MainUsageFormatter.py
src/wai/annotations/core/help/_PluginUsageFormatter.py
src/wai/annotations/core/help/__init__.py
src/wai/annotations/core/help/_format_stage_usage.py
src/wai/annotations/core/help/_plugin_usage_formatter_with_default_start_indent.py
src/wai/annotations/core/logging/_LoggingEnabled.py
src/wai/annotations/core/logging/_StreamLogger.py
