Metadata-Version: 2.1
Name: wai.annotations.core
Version: 0.2.2
Summary: Python library for converting between deep-learning annotation formats.
Home-page: https://github.com/waikato-datamining/wai-annotations-core
Author: Corey Sterling
Author-email: coreytsterling@gmail.com
License: Apache License Version 2.0
Platform: UNKNOWN
Classifier: Development Status :: 4 - Beta
Classifier: License :: OSI Approved :: Apache Software License
Classifier: Topic :: Scientific/Engineering :: Mathematics
Classifier: Programming Language :: Python :: 3
